{"type": "object", "properties": {"type": {"oneOf": [{"type": "null"}, {"type": "string"}]}, "id": {"oneOf": [{"type": "null"}, {"type": "string"}]}, "attributes": {"oneOf": [{"type": "null"}, {"type": "object", "properties": {"lastTokenChars": {"oneOf": [{"type": "null"}, {"type": "string"}]}, "name": {"oneOf": [{"type": "null"}, {"type": "string"}]}, "ipAddress": {"oneOf": [{"type": "null"}, {"type": "string"}]}, "userAgent": {"oneOf": [{"type": "null"}, {"type": "string"}]}, "roles": {"oneOf": [{"type": "null"}, {"type": "array", "items": {"oneOf": [{"type": "null"}, {"type": "string"}]}}]}, "updatedAt": {"oneOf": [{"type": "null"}, {"type": "string"}]}, "createdAt": {"oneOf": [{"type": "null"}, {"type": "string"}]}, "lastAccessedAt": {"oneOf": [{"type": "null"}, {"type": "string"}]}}, "required": ["lastTokenChars", "name", "ipAddress", "userAgent", "roles", "updatedAt", "createdAt", "lastAccessedAt"]}]}, "relationships": {"oneOf": [{"type": "null"}, {"type": "object", "properties": {"org": {"oneOf": [{"type": "null"}, {"type": "object", "properties": {"links": {"oneOf": [{"type": "null"}, {"type": "object", "properties": {"self": {"oneOf": [{"type": "null"}, {"type": "string"}]}}, "required": ["self"]}]}, "data": {"oneOf": [{"type": "null"}, {"type": "object", "properties": {"type": {"oneOf": [{"type": "null"}, {"type": "string"}]}, "id": {"oneOf": [{"type": "null"}, {"type": "string"}]}}, "required": ["type", "id"]}]}}, "required": ["links", "data"]}]}, "user": {"oneOf": [{"type": "null"}, {"type": "object", "properties": {"links": {"oneOf": [{"type": "null"}, {"type": "object", "properties": {"self": {"oneOf": [{"type": "null"}, {"type": "string"}]}}, "required": ["self"]}]}, "data": {"oneOf": [{"type": "null"}, {"type": "object", "properties": {"type": {"oneOf": [{"type": "null"}, {"type": "string"}]}, "id": {"oneOf": [{"type": "null"}, {"type": "string"}]}}, "required": ["type", "id"]}]}}, "required": ["links", "data"]}]}}, "required": ["org", "user"]}]}, "links": {"oneOf": [{"type": "null"}, {"type": "object", "properties": {"self": {"oneOf": [{"type": "null"}, {"type": "string"}]}}, "required": ["self"]}]}, "updatedAt": {"type": "string", "format": "date-time"}}, "required": ["type", "id", "attributes", "relationships", "links"]}