{"type": "object", "properties": {"type": {"oneOf": [{"type": "null"}, {"type": "string"}]}, "id": {"oneOf": [{"type": "null"}, {"type": "string"}]}, "attributes": {"oneOf": [{"type": "null"}, {"type": "object", "properties": {"kustomer": {"oneOf": [{"type": "null"}, {"type": "object", "properties": {"enabled": {"oneOf": [{"type": "null"}, {"type": "boolean"}]}}, "required": ["enabled"]}]}, "google": {"oneOf": [{"type": "null"}, {"type": "object", "properties": {"enabled": {"oneOf": [{"type": "null"}, {"type": "boolean"}]}}, "required": ["enabled"]}]}, "saml": {"oneOf": [{"type": "null"}, {"type": "object", "properties": {"enabled": {"oneOf": [{"type": "null"}, {"type": "boolean"}]}}, "required": ["enabled"]}]}}, "required": ["kustomer", "google", "saml"]}]}, "links": {"oneOf": [{"type": "null"}, {"type": "object", "properties": {"self": {"oneOf": [{"type": "null"}, {"type": "string"}]}}, "required": ["self"]}]}, "updatedAt": {"type": "string", "format": "date-time"}}, "required": ["type", "id", "attributes", "links"]}