{"type": "object", "properties": {"type": {"oneOf": [{"type": "null"}, {"type": "string"}]}, "id": {"oneOf": [{"type": "null"}, {"type": "string"}]}, "attributes": {"oneOf": [{"type": "null"}, {"type": "object", "properties": {"teamName": {"oneOf": [{"type": "null"}, {"type": "string"}]}, "greeting": {"oneOf": [{"type": "null"}, {"type": "string"}]}, "autoreply": {"oneOf": [{"type": "null"}, {"type": "string"}]}, "embedIconUrl": {"oneOf": [{"type": "null"}, {"type": "string"}]}, "embedIconColor": {"oneOf": [{"type": "null"}, {"type": "string"}]}, "enabled": {"oneOf": [{"type": "null"}, {"type": "boolean"}]}, "updatedAt": {"oneOf": [{"type": "null"}, {"type": "string"}]}, "modifiedAt": {"oneOf": [{"type": "null"}, {"type": "string"}]}, "offhoursMessage": {"oneOf": [{"type": "null"}, {"type": "string"}]}, "offhoursImageUrl": {"oneOf": [{"type": "null"}, {"type": "string"}]}, "closableChat": {"oneOf": [{"type": "null"}, {"type": "boolean"}]}, "noHistory": {"oneOf": [{"type": "null"}, {"type": "boolean"}]}, "volumeControl": {"oneOf": [{"type": "null"}, {"type": "object", "properties": {"enabled": {"oneOf": [{"type": "null"}, {"type": "boolean"}]}, "markDoneAfterTimeout": {"oneOf": [{"type": "null"}, {"type": "boolean"}]}, "mode": {"oneOf": [{"type": "null"}, {"type": "string"}]}, "useDynamicWaitMessage": {"oneOf": [{"type": "null"}, {"type": "boolean"}]}, "followUpChannels": {"oneOf": [{"type": "null"}, {"type": "array"}]}, "hideWaitOption": {"oneOf": [{"type": "null"}, {"type": "boolean"}]}}, "required": ["enabled", "markDoneAfterTimeout", "mode", "useDynamicWaitMessage", "followUpChannels", "hideWaitOption"]}]}, "singleSessionChat": {"oneOf": [{"type": "null"}, {"type": "boolean"}]}, "showTypingIndicatorWeb": {"oneOf": [{"type": "null"}, {"type": "boolean"}]}, "showTypingIndicatorCustomerWeb": {"oneOf": [{"type": "null"}, {"type": "boolean"}]}, "showBrandingIdentifier": {"oneOf": [{"type": "null"}, {"type": "boolean"}]}}, "required": ["teamName", "greeting", "autoreply", "embedIconUrl", "embedIconColor", "enabled", "updatedAt", "modifiedAt", "offhoursMessage", "offhoursImageUrl", "closableChat", "noHistory", "volumeControl", "singleSessionChat", "showTypingIndicatorWeb", "showTypingIndicatorCustomerWeb", "showBrandingIdentifier"]}]}, "relationships": {"oneOf": [{"type": "null"}, {"type": "object", "properties": {"org": {"oneOf": [{"type": "null"}, {"type": "object", "properties": {"data": {"oneOf": [{"type": "null"}, {"type": "object", "properties": {"type": {"oneOf": [{"type": "null"}, {"type": "string"}]}, "id": {"oneOf": [{"type": "null"}, {"type": "string"}]}}, "required": ["type", "id"]}]}, "links": {"oneOf": [{"type": "null"}, {"type": "object", "properties": {"self": {"oneOf": [{"type": "null"}, {"type": "string"}]}}, "required": ["self"]}]}}, "required": ["data", "links"]}]}, "modifiedBy": {"oneOf": [{"type": "null"}, {"type": "object", "properties": {"data": {"oneOf": [{"type": "null"}, {"type": "object", "properties": {"type": {"oneOf": [{"type": "null"}, {"type": "string"}]}, "id": {"oneOf": [{"type": "null"}, {"type": "string"}]}}, "required": ["type", "id"]}]}, "links": {"oneOf": [{"type": "null"}, {"type": "object", "properties": {"self": {"oneOf": [{"type": "null"}, {"type": "string"}]}}, "required": ["self"]}]}}, "required": ["data", "links"]}]}}, "required": ["org", "modifiedBy"]}]}, "updatedAt": {"type": "string", "format": "date-time"}}, "required": ["type", "id", "attributes", "relationships"]}